geekar/__init__.py
geekar/app.py
geekar/caged_system.py
geekar/fretboard_ui.py
geekar/geekar_logger.py
geekar/geekar_types.py
geekar/interactive_fretboard_app.py
geekar/interactive_fretboard_app.tcss
geekar/midi.py
geekar-1.0.dist-info/licenses/LICENSE
geekar-1.0.dist-info/METADATA
geekar-1.0.dist-info/WHEEL
geekar-1.0.dist-info/entry_points.txt
geekar-1.0.dist-info/top_level.txt
geekar-1.0.dist-info/RECORD
