Metadata-Version: 2.4
Name: geekar
Version: 1.0
Summary: Guitar learning application for the Linux terminal
Author: Dimitris Kardarakos
Maintainer: Dimitris Kardarakos
License-Expression: AGPL-3.0-only
Project-URL: Homepage, https://codeberg.org/dimkard/geekar
Project-URL: Issues, https://codeberg.org/dimkard/geekar/issues
Keywords: guitar, learn
Classifier: Programming Language :: Python :: 3
Classifier: Development Status :: 5 - Production/Stable
Classifier: Intended Audience :: End Users/Desktop
Classifier: Operating System :: POSIX :: Linux
Requires-Python: >=3.10
License-File: LICENSE
Requires-Dist: textual>=0.32.0
Requires-Dist: pyFluidSynth>=1.3.2
Requires-Dist: music21>=9.1.0
Requires-Dist: pyxdg
Provides-Extra: dev
Requires-Dist: mypy; extra == "dev"
Requires-Dist: pylint; extra == "dev"
Requires-Dist: black; extra == "dev"
Requires-Dist: reuse; extra == "dev"
Dynamic: license-file
